eniric/IOmodule.py
eniric/Qcalculator.py
eniric/__init__.py
eniric/atmosphere.py
eniric/corrections.py
eniric/nIRanalysis.py
eniric/plotting_functions.py
eniric/resample.py
eniric/snr_normalization.py
eniric/utilities.py
eniric-0.5.1.data/scripts/any_spectral_quality.py
eniric-0.5.1.data/scripts/make_test_data.py
eniric-0.5.1.data/scripts/nIR_precision.py
eniric-0.5.1.data/scripts/nIR_run.py
eniric-0.5.1.data/scripts/prepare_data.py
eniric-0.5.1.dist-info/METADATA
eniric-0.5.1.dist-info/RECORD
eniric-0.5.1.dist-info/WHEEL
eniric-0.5.1.dist-info/top_level.txt
eniric_scripts/TAPASproc.py
eniric_scripts/__init__.py
eniric_scripts/any_spectral_quality.py
eniric_scripts/compare_results.py
eniric_scripts/doppler_shift_atmosphere.py
eniric_scripts/make_test_data.py
eniric_scripts/nIR_precision.py
eniric_scripts/nIR_run.py
eniric_scripts/plot_band_midpoints.py
eniric_scripts/pre-precision_check.py
eniric_scripts/prepare_data.py
eniric_scripts/run_all_band_relative_precisions.py
eniric_scripts/split_atmmodel.py
