Metadata-Version: 2.1
Name: eniric
Version: 0.5.1
Summary: Extended NIR Information Content
Home-page: https://github.com/jason-neal/eniric.git
Author: Jason Neal
Author-email: jason.neal@astro.up.pt
License: MIT
Download-URL: https://github.com/jason-neal/eniric.git
Keywords: Astronomy,Radial velocity,Near-infrared spectroscopy,M-dwarfs
Platform: UNKNOWN
Classifier: Development Status :: 4 - Beta
Classifier: Intended Audience :: Science/Research
Classifier: Topic :: Scientific/Engineering :: Astronomy
Classifier: Topic :: Scientific/Engineering :: Physics
Classifier: License :: OSI Approved :: MIT License
Classifier: Programming Language :: Python :: 3 :: Only
Classifier: Programming Language :: Python :: 3.5
Classifier: Programming Language :: Python :: 3.6
Classifier: Natural Language :: English
Classifier: Operating System :: Unix
Classifier: Operating System :: Microsoft :: Windows
Provides-Extra: dev
Provides-Extra: test
Requires-Dist: pytest
Provides-Extra: dev
Requires-Dist: check-manifest; extra == 'dev'
Provides-Extra: test
Requires-Dist: coverage; extra == 'test'
Requires-Dist: pytest; extra == 'test'
Requires-Dist: pytest-cov; extra == 'test'
Requires-Dist: python-coveralls; extra == 'test'
Requires-Dist: hypothesis; extra == 'test'
